{"current_six_sm_array":{"six_current_sm_location":["forms.zohopublic.com \/ referral","google \/ organic","(direct) \/ (none)","google \/ cpc","yahoo \/ organic","bing \/ organic","ahrefs.com \/ referral","answerroot.com \/ referral","api.famous.co \/ referral","app.raindrop.io \/ referral","atavi.com \/ referral","au.enrollbusiness.com \/ referral","au.search.yahoo.com \/ referral","baidu \/ organic","bootstrapstage.com \/ referral","confluence.gerdy.com.au:8090 \/ referral","csima.my.salesforce.com \/ referral","cstime.com \/ referral","duckduckgo \/ organic","ecosia.org \/ organic","engine.presearch.org \/ referral","facebook.com \/ referral","fmclassifieds.com \/ referral","friendster.io \/ referral","fyple.biz \/ referral","l.facebook.com \/ referral","lidcombechurchessoccer.net \/ referral","linkauthority.com \/ referral","linkedin.com \/ referral","localhost \/ referral","m.facebook.com \/ referral","mail.google.com \/ referral","marninixon.com \/ referral","mioola.com \/ referral","org62.lightning.force.com \/ referral","papaly.com \/ referral","ph.search.yahoo.com \/ referral","raindrop.io \/ referral","routeapp.lightning.force.com \/ referral","search.visymo.com \/ referral","searchingzone.com \/ referral","shopistores.com \/ referral","tnasupport.com.au \/ referral","yellowpages.com.au \/ referral","zetco.sharepoint.com \/ referral"],"six_current_sm_goal":["29","9","7","4","2","1","0","0","0","0","0","0","0","0","0","0","0","0","0","0","0","0","0","0","0","0","0","0","0","0","0","0","0","0","0","0","0","0","0","0","0","0","0","0","0"]},"prev_six_sm_array":{"six_prev_sm_location":["google \/ cpc","(direct) \/ (none)","admin.cioreview.com \/ referral","adproceed.com \/ referral","anarhobarnaul.org \/ referral","app.keyword.com \/ referral","ardsearch.com \/ referral","attendancesolutions.netboard.me \/ referral","au.search.yahoo.com \/ referral","aufreeads.com \/ referral","bagtheweb.com \/ referral","baidu \/ organic","baidu.com \/ referral","behance.net \/ referral","bing \/ organic","bookmark2you.com \/ referral","bookmarkextent.com \/ referral","bookmarksmywebs.com \/ referral","bootstrapstage.com \/ referral","canund.com \/ referral","classifiedads.com \/ referral","cn.bing.com \/ referral","coggle.it \/ referral","connect.symfony.com \/ referral","creativelive.com \/ referral","cstime.com \/ referral","digital.dealsclassified.online \/ referral","digitalleaf.teamwork.com \/ referral","duckduckgo \/ organic","easierbookmark.com \/ referral","eloadstore.com \/ referral","en.gravatar.com \/ referral","facebook.com \/ referral","favable.com \/ referral","findalion.com.au \/ referral","forms.zohopublic.com \/ referral","globalclassified.net \/ referral","goodfirms.co \/ referral","google \/ organic","google.com \/ referral","hi.locanto.com \/ referral","in.search.yahoo.com \/ referral","izito.ws \/ referral","jhdiy.net \/ referral","keyword.com \/ referral","l.facebook.com \/ referral","l.workplace.com \/ referral","lidcombechurchessoccer.net \/ referral","linkauthority.com \/ referral","linkedin.com \/ referral","list.ly \/ referral","localbusinesslisting.org \/ referral","m.facebook.com \/ referral","mail.google.com \/ referral","mind42.com \/ referral","mioola.com \/ referral","my.bundyplus.com.au \/ referral","nogarolerocca.net \/ referral","nyulawglobal.com \/ referral","pligg.wtguru.com \/ referral","portfoliopen.com \/ referral","promoteproject.com \/ referral","refind.com \/ referral","routeapp.lightning.force.com \/ referral","searchingzone.com \/ referral","seedandspark.com \/ referral","seofiverr.com \/ referral","seooptions.ml \/ referral","shieldact.com \/ referral","simple-affiliate \/ referral","skloog.com \/ referral","smoweb.samaysawara.in \/ referral","t.co \/ referral","tanda.workplace.com \/ referral","tefter.io \/ referral","time-attendance-solutions.sitey.me \/ referral","timeandattendance.artweb.com \/ referral","timeattendau.livejournal.com \/ referral","tna5.com \/ referral","tnasoftware.com \/ referral","tnasupport.com.au \/ referral","trumpbookusa.com \/ referral","xpblogger.com \/ referral","yahoo \/ organic","yahoodirectory.in \/ referral","yandex.com.tr \/ referral","yellowpages.com.au \/ referral","zeef.com \/ referral"],"six_prev_sm_goal":["1","0","0","0","0","0","0","0","0","0","0","0","0","0","0","0","0","0","0","0","0","0","0","0","0","0","0","0","0","0","0","0","0","0","0","0","0","0","0","0","0","0","0","0","0","0","0","0","0","0","0","0","0","0","0","0","0","0","0","0","0","0","0","0","0","0","0","0","0","0","0","0","0","0","0","0","0","0","0","0","0","0","0","0","0","0","0","0"]},"current_six_sm_organic_array":{"six_current_organic_sm_location":["bing \/ organic","google \/ organic","yahoo \/ organic"],"six_current_organic_sm_goal":["1","9","2"]},"prev_six_sm_organic_array":{"six_prev_organic_sm_location":[],"six_prev_organic_sm_goal":[]}}