{"current_three_sm_array":{"three_current_sm_location":["google \/ cpc","(direct) \/ (none)","shareasale-analytics.com \/ referral","google \/ organic","simplycodes.com \/ referral","abandoned_cart \/ email","l.facebook.com \/ referral","shop_app \/ (not set)","youtube.com \/ referral","pinterest.com \/ referral","Welcome Series \/ email","facebook.com \/ referral","Facebook \/ Social","l.instagram.com \/ referral","baidu \/ organic","pinterest.ca \/ referral","pinterest.fr \/ referral","dunali.myshopify.com \/ referral","aamz1.mabangerp.com \/ referral","bing \/ organic","cmp4e25o2hxt94a7-27553955892.shopifypreview.com \/ referral","judge.me \/ referral","m.facebook.com \/ referral","hooks.stripe.com \/ referral","ahr.theposttoday.com \/ referral","instagram.com \/ referral","Fulfilled Order-2021.1.29 Sample2 \/ email","pinterest.co.uk \/ referral","Abandoned Cart \/ email","data.fmtc.co \/ referral","laylacoco.myfunpinpin.com \/ referral","snapchat.com \/ referral","Abandoned Customer Sample1 \/ email","Facebook \/ Converison","Newsletter Sample1 \/ email","ahr1.buyseo.shop \/ referral","athenaful.com \/ referral","basecamp.com \/ referral","couponbirds.com \/ referral","judgeme \/ referral","koala-apps-koala-inspector \/ koala-apps-koala-inspector","platadmin.wickfire.com \/ referral","sociablelabs.com \/ referral","yahoo \/ organic","0refer.com \/ referral","47.106.135.139 \/ referral","Customer Thank You \/ email","Facebook \/ Remarketing","Fulfilled Order-2021.1.22 Sample1 \/ email","Fulfilled Order-2021.1.29 Sample3 \/ email","admin.shidaiapps.com \/ referral","ahr.tonnyseo.com \/ referral","autoblog.top \/ referral","blankrefer.com \/ referral","br.pinterest.com \/ referral","cn.bing.com \/ referral","dealdrop-tools.herokuapp.com \/ referral","didyouknowfashion.com \/ referral","directory.fmtc.co \/ referral","divinebeautytips.com \/ referral","dmmspy.com \/ referral","duckduckgo \/ organic","ecosia.org \/ organic","eu26.lightning.force.com \/ referral","fmtc.co \/ referral","google \/ (not set)","gopher.com \/ referral","haloroar.com \/ referral","harpoon.zdtc.global \/ referral","in.pinterest.com \/ referral","jacketformen.net \/ referral","jira.purelogics.net \/ referral","judgeme \/ email","judgeme \/ user_profile","kidneykidney.com \/ referral","lifestylebyps.com \/ referral","lifestyledezine.com \/ referral","linkauthority.com \/ referral","linktr.ee \/ referral","mail.google.com \/ referral","milled.com \/ referral","mybeautifuladventures.com \/ referral","nexus.demand.io \/ referral","nl.pinterest.com \/ referral","nullrefer.com \/ referral","odessaguide.net \/ referral","offers.com \/ referral","officialroyalwedding2011.org \/ referral","pinterest.ph \/ referral","pinterest.pt \/ referral","pinterest.se \/ referral","retailmenot.com \/ referral","sellercenter.io \/ referral","shopistores.com \/ referral","sogou \/ organic","spyspyspy.net \/ referral","stephilareine.com \/ referral","tierradecinefagos.com \/ referral","ufo.worksection.com \/ referral","webmail.westnet.com.au \/ referral","womensbeautyoffers.com \/ referral"],"three_current_sm_goal":["2649","960","206","170","61","41","32","30","28","20","17","14","13","11","10","9","9","8","7","7","6","6","6","5","4","4","3","3","2","2","2","2","1","1","1","1","1","1","1","1","1","1","1","1","0","0","0","0","0","0","0","0","0","0","0","0","0","0","0","0","0","0","0","0","0","0","0","0","0","0","0","0","0","0","0","0","0","0","0","0","0","0","0","0","0","0","0","0","0","0","0","0","0","0","0","0","0","0","0","0","0"]},"prev_three_sm_array":{"three_prev_sm_location":["google \/ cpc","(direct) \/ (none)","google \/ organic","m.facebook.com \/ referral","shop_app \/ (not set)","instagram.com \/ referral","abandoned_cart \/ email","judge.me \/ referral","Welcome Series \/ email","klaviyo.com \/ referral","Facebook \/ Social","Advertisement \/ email","bing \/ organic","l.facebook.com \/ referral","pinterest.com \/ referral","paypal.com \/ referral","Abandoned Customer Sample1 \/ email","Repeat Buyers \/ email","facebook.com \/ referral","Abandoned Cart \/ email","Customer Thank You \/ email","judgeme \/ email","l.instagram.com \/ referral","Newsletter Sample1 \/ email","Fulfilled Order-2021.1.22 Sample1 \/ email","dunali-fr.myshopify.com \/ referral","Newsletter \/ email","youtube.com \/ referral","Newsletter Sample2 \/ email","Abandoned Customer Sample2 \/ email","Newsletter Sample3 \/ email","googleweblight.com \/ referral","pinterest.co.uk \/ referral","mail.google.com \/ referral","qvay.app.link \/ referral","lm.facebook.com \/ referral","Facebook \/ Remarketing","aamz.mabangerp.com \/ referral","codeblackbelt.com \/ referral","my.stripo.email \/ referral","pinterest.com.mx \/ referral","Abandoned Customer \/ email","Facebook \/ Converison","Fulfilled Order-2021.1.22 \/ email","New Subscribers \/ email","addicfashion.com \/ referral","admin.fashiontiy.com \/ referral","ads.google.com \/ referral","adwords.corp.google.com \/ referral","ahr.theposttoday.com \/ referral","app.adspy.com \/ referral","baidu \/ organic","brand-makers.org \/ referral","business.facebook.com \/ referral","cn.bing.com \/ referral","couponwcode.com \/ referral","dmmspy.com \/ referral","docs.qq.com \/ referral","dunali.co.uk \/ referral","emailsystem.ignoprg.ir \/ referral","globaliso.lightning.force.com \/ referral","goaffpro.com \/ referral","ixspy.com \/ referral","judgeme \/ referral","lemonjewels.com \/ referral","m.youtube.com \/ referral","mail.qq.com \/ referral","officialroyalwedding2011.org \/ referral","pinterest.fr \/ referral","sellercenter.io \/ referral","snapchat.com \/ referral","sogou \/ organic","spyspyspy.net \/ referral","t.co \/ referral","thenburn.com \/ referral","trustpilot \/ company_profile","yahoo \/ organic"],"three_prev_sm_goal":["6363","2218","300","102","84","70","53","47","45","38","36","28","28","27","27","26","20","20","20","18","16","16","15","9","8","8","7","7","6","5","5","5","5","3","3","2","1","1","1","1","1","0","0","0","0","0","0","0","0","0","0","0","0","0","0","0","0","0","0","0","0","0","0","0","0","0","0","0","0","0","0","0","0","0","0","0","0"]},"current_three_sm_organic_array":{"three_current_organic_sm_location":["baidu \/ organic","bing \/ organic","google \/ organic","yahoo \/ organic"],"three_current_organic_sm_goal":["10","7","170","1"]},"prev_three_sm_organic_array":{"three_prev_organic_sm_location":["bing \/ organic","google \/ organic"],"three_prev_organic_sm_goal":["28","300"]}}