{"month_device_array":[{"month_device_keys":"MOBILE","month_device_clicks":289,"month_device_impressions":13279,"month_device_ctr":0.021763687024625347,"month_device_position":19.992770539950296},{"month_device_keys":"DESKTOP","month_device_clicks":190,"month_device_impressions":11638,"month_device_ctr":0.016325829180271523,"month_device_position":41.19393366557828},{"month_device_keys":"TABLET","month_device_clicks":15,"month_device_impressions":315,"month_device_ctr":0.047619047619047616,"month_device_position":12.60952380952381}],"three_device_array":[{"three_device_keys":"MOBILE","three_device_clicks":896,"three_device_impressions":37912,"three_device_ctr":0.023633677991137372,"three_device_position":18.045078075543362},{"three_device_keys":"DESKTOP","three_device_clicks":685,"three_device_impressions":35538,"three_device_ctr":0.01927514210141257,"three_device_position":41.15861894310316},{"three_device_keys":"TABLET","three_device_clicks":45,"three_device_impressions":1106,"three_device_ctr":0.0406871609403255,"three_device_position":11.373417721518987}],"six_device_array":[{"six_device_keys":"MOBILE","six_device_clicks":1740,"six_device_impressions":66957,"six_device_ctr":0.02598682736681751,"six_device_position":18.109368699314487},{"six_device_keys":"DESKTOP","six_device_clicks":1292,"six_device_impressions":68320,"six_device_ctr":0.018911007025761123,"six_device_position":44.65393735362998},{"six_device_keys":"TABLET","six_device_clicks":84,"six_device_impressions":2154,"six_device_ctr":0.03899721448467967,"six_device_position":16.64020427112349}],"nine_device_array":[{"nine_device_keys":"MOBILE","nine_device_clicks":2441,"nine_device_impressions":95415,"nine_device_ctr":0.02558297961536446,"nine_device_position":20.347869831787456},{"nine_device_keys":"DESKTOP","nine_device_clicks":1779,"nine_device_impressions":104799,"nine_device_ctr":0.016975352818252083,"nine_device_position":47.92933138674987},{"nine_device_keys":"TABLET","nine_device_clicks":121,"nine_device_impressions":3199,"nine_device_ctr":0.03782432010003126,"nine_device_position":21.66051891216005}],"year_device_array":[{"year_device_keys":"MOBILE","year_device_clicks":2794,"year_device_impressions":112887,"year_device_ctr":0.024750414130945104,"year_device_position":19.707627981964265},{"year_device_keys":"DESKTOP","year_device_clicks":2080,"year_device_impressions":123937,"year_device_ctr":0.016782720253031784,"year_device_position":47.13146195244358},{"year_device_keys":"TABLET","year_device_clicks":134,"year_device_impressions":3743,"year_device_ctr":0.03580016029922522,"year_device_position":20.94362810579749}],"two_year_device_array":[{"two_year_device_keys":"MOBILE","two_year_device_clicks":2794,"two_year_device_impressions":112887,"two_year_device_ctr":0.024750414130945104,"two_year_device_position":19.707627981964265},{"two_year_device_keys":"DESKTOP","two_year_device_clicks":2080,"two_year_device_impressions":123937,"two_year_device_ctr":0.016782720253031784,"two_year_device_position":47.13146195244358},{"two_year_device_keys":"TABLET","two_year_device_clicks":134,"two_year_device_impressions":3743,"two_year_device_ctr":0.03580016029922522,"two_year_device_position":20.94362810579749}]}