{"current_twoyear_array":{"twoyear_current_location":["\/thank-you\/","\/about-us\/contact-us\/","\/about-us\/contact-us\/?fbclid=IwAR0eC8QiP1yfz9hy4PemWT2xVLYRQ6nHb2HYgv0xva_4kXYCJgoFuYVXqIY","\/about-us\/contact-us\/?fbclid=IwAR0l0GvmDBUEuaWTclXkAE7uBqL3Bq80GSLwViBBTOqfZZJpCXHi_Tb48s4","\/about-us\/contact-us\/?fbclid=IwAR24MGnk8owvGBLGT4Y6G-iski78MfRl2Skkqo_7YV7FGgn3DqLRp24MgUA","\/about-us\/contact-us\/?fbclid=IwAR27fD2T-7X8kUxycpET3jeknfJDDtiiOeDJDJV7xhZqZKdA0BJY6pH_b64"],"twoyear_current_goal":["683","664","1","1","1","1"]},"prev_twoyear_array":{"twoyear_prev_location":["\/about-us\/contact-us\/","\/thank-you\/","\/about-us\/contact-us\/?cl="],"twoyear_prev_goal":["1226","235","2"]},"current_twoyear_organic_array":{"twoyear_current_organic_location":["\/about-us\/contact-us\/","\/thank-you\/"],"twoyear_current_organic_goal":["254","154"]},"prev_twoyear_organic_array":{"twoyear_prev_organic_location":["\/about-us\/contact-us\/","\/thank-you\/"],"twoyear_prev_organic_goal":["46","7"]}}