{"month_query_array":[{"month_query_keys":"party tent rentals","month_query_clicks":61,"month_query_impressions":438,"month_query_ctr":0.13926940639269406,"month_query_position":5.981735159817352},{"month_query_keys":"pop up party tent hire","month_query_clicks":47,"month_query_impressions":246,"month_query_ctr":0.1910569105691057,"month_query_position":2.5528455284552845},{"month_query_keys":"pop up party tent","month_query_clicks":46,"month_query_impressions":821,"month_query_ctr":0.05602923264311815,"month_query_position":17.38124238733252},{"month_query_keys":"blow up party tent","month_query_clicks":28,"month_query_impressions":189,"month_query_ctr":0.14814814814814814,"month_query_position":2.1904761904761907},{"month_query_keys":"inflatable party tent hire","month_query_clicks":27,"month_query_impressions":263,"month_query_ctr":0.10266159695817491,"month_query_position":7.547528517110266},{"month_query_keys":"outdoor party hire","month_query_clicks":22,"month_query_impressions":398,"month_query_ctr":0.05527638190954774,"month_query_position":15.271356783919598},{"month_query_keys":"garden party tent hire","month_query_clicks":21,"month_query_impressions":278,"month_query_ctr":0.07553956834532374,"month_query_position":9.723021582733812},{"month_query_keys":"party tent hire","month_query_clicks":21,"month_query_impressions":792,"month_query_ctr":0.026515151515151516,"month_query_position":18.232323232323232},{"month_query_keys":"party tents for rent","month_query_clicks":20,"month_query_impressions":188,"month_query_ctr":0.10638297872340426,"month_query_position":6.76595744680851},{"month_query_keys":"pop up party","month_query_clicks":18,"month_query_impressions":156,"month_query_ctr":0.11538461538461539,"month_query_position":9.23076923076923}],"three_query_array":[{"three_query_keys":"party tent hire","three_query_clicks":168,"three_query_impressions":3705,"three_query_ctr":0.045344129554655874,"three_query_position":15.96464237516869},{"three_query_keys":"party tent rentals","three_query_clicks":144,"three_query_impressions":1230,"three_query_ctr":0.11707317073170732,"three_query_position":5.786178861788618},{"three_query_keys":"pop up party tent hire","three_query_clicks":135,"three_query_impressions":692,"three_query_ctr":0.19508670520231214,"three_query_position":2.913294797687861},{"three_query_keys":"pop up party tent","three_query_clicks":105,"three_query_impressions":2680,"three_query_ctr":0.03917910447761194,"three_query_position":18.966044776119404},{"three_query_keys":"outdoor party hire","three_query_clicks":86,"three_query_impressions":1274,"three_query_ctr":0.06750392464678179,"three_query_position":11.820251177394034},{"three_query_keys":"inflatable party tent hire","three_query_clicks":81,"three_query_impressions":847,"three_query_ctr":0.09563164108618655,"three_query_position":7.54073199527745},{"three_query_keys":"pop up nightclub hire near me","three_query_clicks":81,"three_query_impressions":1136,"three_query_ctr":0.07130281690140845,"three_query_position":8.68661971830986},{"three_query_keys":"blow up party tent","three_query_clicks":62,"three_query_impressions":568,"three_query_ctr":0.10915492957746478,"three_query_position":2.130281690140845},{"three_query_keys":"party tents for rent","three_query_clicks":61,"three_query_impressions":493,"three_query_ctr":0.12373225152129817,"three_query_position":6.251521298174442},{"three_query_keys":"garden party tent hire","three_query_clicks":58,"three_query_impressions":917,"three_query_ctr":0.06324972737186478,"three_query_position":8.380588876772084}],"six_query_array":[{"six_query_keys":"party tent hire","six_query_clicks":397,"six_query_impressions":7126,"six_query_ctr":0.055711479090653944,"six_query_position":15.59963513892787},{"six_query_keys":"party tent rentals","six_query_clicks":306,"six_query_impressions":2041,"six_query_ctr":0.1499265066144047,"six_query_position":5.365997060264577},{"six_query_keys":"outdoor party hire","six_query_clicks":225,"six_query_impressions":2395,"six_query_ctr":0.09394572025052192,"six_query_position":19.09812108559499},{"six_query_keys":"pop up party tent hire","six_query_clicks":199,"six_query_impressions":1036,"six_query_ctr":0.1920849420849421,"six_query_position":2.917953667953668},{"six_query_keys":"garden party tent hire","six_query_clicks":172,"six_query_impressions":1787,"six_query_ctr":0.09625069949636261,"six_query_position":6.330721880246223},{"six_query_keys":"pop up party tent","six_query_clicks":172,"six_query_impressions":4489,"six_query_ctr":0.03831588327021608,"six_query_position":19.749387391401203},{"six_query_keys":"party tents for rent","six_query_clicks":129,"six_query_impressions":846,"six_query_ctr":0.1524822695035461,"six_query_position":5.612293144208038},{"six_query_keys":"inflatable party tent hire","six_query_clicks":124,"six_query_impressions":1361,"six_query_ctr":0.09110947832476121,"six_query_position":6.858927259368111},{"six_query_keys":"blow up party tent","six_query_clicks":111,"six_query_impressions":902,"six_query_ctr":0.12305986696230599,"six_query_position":2.0532150776053215},{"six_query_keys":"party tent hire near me","six_query_clicks":104,"six_query_impressions":1945,"six_query_ctr":0.05347043701799486,"six_query_position":11.07917737789203}],"nine_query_array":[{"nine_query_keys":"party tent hire","nine_query_clicks":432,"nine_query_impressions":8050,"nine_query_ctr":0.053664596273291926,"nine_query_position":16.546583850931675},{"nine_query_keys":"party tent rentals","nine_query_clicks":336,"nine_query_impressions":2610,"nine_query_ctr":0.12873563218390804,"nine_query_position":5.498850574712644},{"nine_query_keys":"outdoor party hire","nine_query_clicks":229,"nine_query_impressions":3034,"nine_query_ctr":0.07547791694133157,"nine_query_position":29.407053394858274},{"nine_query_keys":"pop up party tent hire","nine_query_clicks":208,"nine_query_impressions":1097,"nine_query_ctr":0.18960802187784867,"nine_query_position":2.872379216043756},{"nine_query_keys":"pop up party tent","nine_query_clicks":196,"nine_query_impressions":6051,"nine_query_ctr":0.03239134027433482,"nine_query_position":21.185919682697076},{"nine_query_keys":"garden party tent hire","nine_query_clicks":192,"nine_query_impressions":2260,"nine_query_ctr":0.08495575221238938,"nine_query_position":6.911504424778761},{"nine_query_keys":"party tents for rent","nine_query_clicks":143,"nine_query_impressions":967,"nine_query_ctr":0.14788004136504654,"nine_query_position":6.382626680455015},{"nine_query_keys":"inflatable party tent hire","nine_query_clicks":127,"nine_query_impressions":1493,"nine_query_ctr":0.08506363027461487,"nine_query_position":6.786336235766912},{"nine_query_keys":"blow up party tent","nine_query_clicks":124,"nine_query_impressions":1001,"nine_query_ctr":0.12387612387612387,"nine_query_position":2.25974025974026},{"nine_query_keys":"party tent hire near me","nine_query_clicks":111,"nine_query_impressions":2058,"nine_query_ctr":0.05393586005830904,"nine_query_position":11.263848396501457}],"one_year_query_array":[{"one_year_query_keys":"party tent rentals","one_year_query_clicks":442,"one_year_query_impressions":3590,"one_year_query_ctr":0.12311977715877437,"one_year_query_position":6.349025069637883},{"one_year_query_keys":"party tent hire","one_year_query_clicks":440,"one_year_query_impressions":8773,"one_year_query_ctr":0.050153881226490366,"one_year_query_position":17.943006953151716},{"one_year_query_keys":"pop up party tent","one_year_query_clicks":267,"one_year_query_impressions":8073,"one_year_query_ctr":0.033073206986250464,"one_year_query_position":20.548866592344854},{"one_year_query_keys":"pop up party tent hire","one_year_query_clicks":255,"one_year_query_impressions":1271,"one_year_query_ctr":0.2006294256490952,"one_year_query_position":2.7970102281667977},{"one_year_query_keys":"outdoor party hire","one_year_query_clicks":230,"one_year_query_impressions":3310,"one_year_query_ctr":0.06948640483383686,"one_year_query_position":32.62900302114804},{"one_year_query_keys":"garden party tent hire","one_year_query_clicks":194,"one_year_query_impressions":2436,"one_year_query_ctr":0.07963875205254516,"one_year_query_position":8.189655172413794},{"one_year_query_keys":"pop up nightclub hire","one_year_query_clicks":165,"one_year_query_impressions":1914,"one_year_query_ctr":0.08620689655172414,"one_year_query_position":6.51828631138976},{"one_year_query_keys":"inflatable party tent hire","one_year_query_clicks":161,"one_year_query_impressions":1780,"one_year_query_ctr":0.09044943820224718,"one_year_query_position":6.662359550561797},{"one_year_query_keys":"blow up party tent","one_year_query_clicks":159,"one_year_query_impressions":1280,"one_year_query_ctr":0.12421875,"one_year_query_position":2.91484375},{"one_year_query_keys":"party tents for rent","one_year_query_clicks":158,"one_year_query_impressions":1223,"one_year_query_ctr":0.12919051512673754,"one_year_query_position":7.342600163532298}],"two_year_query_array":[{"query_keys":"party tent rentals","query_clicks":455,"query_impressions":4410,"query_ctr":0.10317460317460317,"query_position":7.256009070294785},{"query_keys":"party tent hire","query_clicks":442,"query_impressions":9774,"query_ctr":0.045222017597708206,"query_position":21.617147534274608},{"query_keys":"pop up party tent","query_clicks":315,"query_impressions":10122,"query_ctr":0.03112033195020747,"query_position":21.09118751234934},{"query_keys":"pop up party tent hire","query_clicks":281,"query_impressions":1381,"query_ctr":0.20347574221578565,"query_position":2.732802317161477},{"query_keys":"outdoor party hire","query_clicks":230,"query_impressions":3382,"query_ctr":0.06800709639266705,"query_position":32.77114133648729},{"query_keys":"pop up nightclub hire","query_clicks":221,"query_impressions":2696,"query_ctr":0.081973293768546,"query_position":6.765578635014837},{"query_keys":"garden party tent hire","query_clicks":194,"query_impressions":2510,"query_ctr":0.07729083665338646,"query_position":9.549003984063745},{"query_keys":"inflatable party tent hire","query_clicks":164,"query_impressions":1837,"query_ctr":0.08927599346761024,"query_position":7.107784431137724},{"query_keys":"pop up party","query_clicks":161,"query_impressions":1335,"query_ctr":0.12059925093632959,"query_position":13.489887640449439},{"query_keys":"blow up party tent","query_clicks":160,"query_impressions":1306,"query_ctr":0.1225114854517611,"query_position":3.098009188361409}]}