{"current_twoyear_array":{"twoyear_current_location":["\/purchase\/invoice.html","\/form\/contact-us-thank-you\/"],"twoyear_current_goal":["7988","1"]},"prev_twoyear_array":{"twoyear_prev_location":["\/purchase\/invoice.html"],"twoyear_prev_goal":["2475"]},"current_twoyear_organic_array":{"twoyear_current_organic_location":["\/form\/contact-us-thank-you\/","\/purchase\/invoice.html"],"twoyear_current_organic_goal":["1","1558"]},"prev_twoyear_organic_array":{"twoyear_prev_organic_location":["\/purchase\/invoice.html"],"twoyear_prev_organic_goal":["58"]}}