{"month_query_array":[{"month_query_keys":"tulieve photography","month_query_clicks":20,"month_query_impressions":35,"month_query_ctr":0.5714285714285714,"month_query_position":1.0285714285714285},{"month_query_keys":"tulieve","month_query_clicks":8,"month_query_impressions":124,"month_query_ctr":0.06451612903225806,"month_query_position":2.1693548387096775},{"month_query_keys":"family photographer port douglas","month_query_clicks":7,"month_query_impressions":31,"month_query_ctr":0.22580645161290322,"month_query_position":2.5483870967741935},{"month_query_keys":"cairns wedding photographer","month_query_clicks":6,"month_query_impressions":224,"month_query_ctr":0.026785714285714284,"month_query_position":4.955357142857142},{"month_query_keys":"videographer cairns","month_query_clicks":6,"month_query_impressions":50,"month_query_ctr":0.12,"month_query_position":5.6},{"month_query_keys":"wedding venues cairns tablelands","month_query_clicks":6,"month_query_impressions":267,"month_query_ctr":0.02247191011235955,"month_query_position":1.898876404494382},{"month_query_keys":"elope cairns","month_query_clicks":5,"month_query_impressions":28,"month_query_ctr":0.17857142857142858,"month_query_position":5.964285714285714},{"month_query_keys":"photographer cairns","month_query_clicks":5,"month_query_impressions":237,"month_query_ctr":0.02109704641350211,"month_query_position":8.725738396624472},{"month_query_keys":"cairns wedding videographer","month_query_clicks":4,"month_query_impressions":26,"month_query_ctr":0.15384615384615385,"month_query_position":3},{"month_query_keys":"palm cove elopement","month_query_clicks":4,"month_query_impressions":18,"month_query_ctr":0.2222222222222222,"month_query_position":2.5555555555555554}],"three_query_array":[{"three_query_keys":"tulieve photography","three_query_clicks":73,"three_query_impressions":125,"three_query_ctr":0.584,"three_query_position":1.024},{"three_query_keys":"palm cove elopement","three_query_clicks":24,"three_query_impressions":88,"three_query_ctr":0.2727272727272727,"three_query_position":2.2613636363636367},{"three_query_keys":"tulieve","three_query_clicks":23,"three_query_impressions":463,"three_query_ctr":0.04967602591792657,"three_query_position":1.8466522678185746},{"three_query_keys":"cairns wedding photographer","three_query_clicks":22,"three_query_impressions":641,"three_query_ctr":0.0343213728549142,"three_query_position":5.285491419656786},{"three_query_keys":"wedding venues cairns tablelands","three_query_clicks":15,"three_query_impressions":880,"three_query_ctr":0.017045454545454544,"three_query_position":2.206818181818182},{"three_query_keys":"photographer cairns","three_query_clicks":11,"three_query_impressions":628,"three_query_ctr":0.01751592356687898,"three_query_position":6.898089171974522},{"three_query_keys":"videographer cairns","three_query_clicks":11,"three_query_impressions":122,"three_query_ctr":0.09016393442622951,"three_query_position":4.032786885245901},{"three_query_keys":"wedding photographer hobart","three_query_clicks":11,"three_query_impressions":265,"three_query_ctr":0.04150943396226415,"three_query_position":6.362264150943396},{"three_query_keys":"family photography cairns","three_query_clicks":10,"three_query_impressions":149,"three_query_ctr":0.06711409395973154,"three_query_position":4.201342281879194},{"three_query_keys":"family photographer cairns","three_query_clicks":9,"three_query_impressions":128,"three_query_ctr":0.0703125,"three_query_position":2.8203125}],"six_query_array":[{"six_query_keys":"tulieve photography","six_query_clicks":138,"six_query_impressions":242,"six_query_ctr":0.5702479338842975,"six_query_position":1.0206611570247934},{"six_query_keys":"palm cove elopement","six_query_clicks":43,"six_query_impressions":179,"six_query_ctr":0.24022346368715083,"six_query_position":2.6201117318435756},{"six_query_keys":"cairns wedding photographer","six_query_clicks":36,"six_query_impressions":1089,"six_query_ctr":0.03305785123966942,"six_query_position":4.859504132231405},{"six_query_keys":"wedding venues cairns tablelands","six_query_clicks":33,"six_query_impressions":1707,"six_query_ctr":0.019332161687170474,"six_query_position":2.471001757469244},{"six_query_keys":"tulieve","six_query_clicks":30,"six_query_impressions":942,"six_query_ctr":0.03184713375796178,"six_query_position":2.1210191082802545},{"six_query_keys":"wedding photographer tasmania","six_query_clicks":27,"six_query_impressions":751,"six_query_ctr":0.03595206391478029,"six_query_position":6.005326231691079},{"six_query_keys":"photographer cairns","six_query_clicks":26,"six_query_impressions":1374,"six_query_ctr":0.018922852983988356,"six_query_position":5.543668122270742},{"six_query_keys":"videographer cairns","six_query_clicks":26,"six_query_impressions":266,"six_query_ctr":0.09774436090225563,"six_query_position":3.6165413533834587},{"six_query_keys":"wedding photographer hobart","six_query_clicks":26,"six_query_impressions":576,"six_query_ctr":0.04513888888888889,"six_query_position":7.546875},{"six_query_keys":"tasmania wedding photographer","six_query_clicks":22,"six_query_impressions":501,"six_query_ctr":0.043912175648702596,"six_query_position":5.54690618762475}],"nine_query_array":[{"nine_query_keys":"tulieve photography","nine_query_clicks":175,"nine_query_impressions":316,"nine_query_ctr":0.5537974683544303,"nine_query_position":1.0284810126582278},{"nine_query_keys":"tulieve","nine_query_clicks":61,"nine_query_impressions":1318,"nine_query_ctr":0.04628224582701062,"nine_query_position":1.8694992412746587},{"nine_query_keys":"cairns wedding photographer","nine_query_clicks":52,"nine_query_impressions":2225,"nine_query_ctr":0.023370786516853932,"nine_query_position":5.271460674157304},{"nine_query_keys":"palm cove elopement","nine_query_clicks":43,"nine_query_impressions":185,"nine_query_ctr":0.23243243243243245,"nine_query_position":2.918918918918919},{"nine_query_keys":"wedding venues cairns tablelands","nine_query_clicks":37,"nine_query_impressions":2023,"nine_query_ctr":0.01828966880869995,"nine_query_position":3.531883341571923},{"nine_query_keys":"videographer cairns","nine_query_clicks":32,"nine_query_impressions":361,"nine_query_ctr":0.0886426592797784,"nine_query_position":3.6952908587257616},{"nine_query_keys":"photographer cairns","nine_query_clicks":31,"nine_query_impressions":1938,"nine_query_ctr":0.015995872033023734,"nine_query_position":6.147574819401445},{"nine_query_keys":"wedding photographer hobart","nine_query_clicks":31,"nine_query_impressions":692,"nine_query_ctr":0.044797687861271675,"nine_query_position":8.614161849710982},{"nine_query_keys":"wedding photographer tasmania","nine_query_clicks":29,"nine_query_impressions":976,"nine_query_ctr":0.02971311475409836,"nine_query_position":8.35655737704918},{"nine_query_keys":"cairns wedding videographer","nine_query_clicks":28,"nine_query_impressions":254,"nine_query_ctr":0.11023622047244094,"nine_query_position":2.795275590551181}],"one_year_query_array":[{"one_year_query_keys":"tulieve photography","one_year_query_clicks":218,"one_year_query_impressions":392,"one_year_query_ctr":0.5561224489795918,"one_year_query_position":1.211734693877551},{"one_year_query_keys":"tulieve","one_year_query_clicks":95,"one_year_query_impressions":1702,"one_year_query_ctr":0.05581668625146886,"one_year_query_position":1.9441833137485312},{"one_year_query_keys":"cairns wedding photographer","one_year_query_clicks":74,"one_year_query_impressions":2943,"one_year_query_ctr":0.025144410465511382,"one_year_query_position":5.146449201495073},{"one_year_query_keys":"palm cove elopement","one_year_query_clicks":43,"one_year_query_impressions":185,"one_year_query_ctr":0.23243243243243245,"one_year_query_position":2.918918918918919},{"one_year_query_keys":"videographer cairns","one_year_query_clicks":43,"one_year_query_impressions":460,"one_year_query_ctr":0.09347826086956522,"one_year_query_position":3.5},{"one_year_query_keys":"wedding venues cairns tablelands","one_year_query_clicks":37,"one_year_query_impressions":2023,"one_year_query_ctr":0.01828966880869995,"one_year_query_position":3.531883341571923},{"one_year_query_keys":"cairns wedding videographer","one_year_query_clicks":35,"one_year_query_impressions":313,"one_year_query_ctr":0.11182108626198083,"one_year_query_position":2.6773162939297124},{"one_year_query_keys":"photographer cairns","one_year_query_clicks":35,"one_year_query_impressions":2544,"one_year_query_ctr":0.013757861635220126,"one_year_query_position":7.229559748427673},{"one_year_query_keys":"wedding photographer cairns","one_year_query_clicks":32,"one_year_query_impressions":1319,"one_year_query_ctr":0.024260803639120546,"one_year_query_position":5.561031084154663},{"one_year_query_keys":"wedding photographer hobart","one_year_query_clicks":32,"one_year_query_impressions":702,"one_year_query_ctr":0.045584045584045586,"one_year_query_position":8.907407407407408}],"two_year_query_array":[{"query_keys":"tulieve photography","query_clicks":292,"query_impressions":520,"query_ctr":0.5615384615384615,"query_position":1.5576923076923077},{"query_keys":"tulieve","query_clicks":125,"query_impressions":2106,"query_ctr":0.059354226020892686,"query_position":2.0788224121557457},{"query_keys":"cairns wedding photographer","query_clicks":104,"query_impressions":3613,"query_ctr":0.028784943260448382,"query_position":5.693883199557154},{"query_keys":"videographer cairns","query_clicks":48,"query_impressions":585,"query_ctr":0.08205128205128205,"query_position":4.172649572649572},{"query_keys":"cairns wedding videographer","query_clicks":46,"query_impressions":391,"query_ctr":0.11764705882352941,"query_position":2.629156010230179},{"query_keys":"palm cove elopement","query_clicks":43,"query_impressions":185,"query_ctr":0.23243243243243245,"query_position":2.918918918918919},{"query_keys":"port douglas wedding photography","query_clicks":38,"query_impressions":2242,"query_ctr":0.01694915254237288,"query_position":6.294380017841213},{"query_keys":"wedding photographer cairns","query_clicks":37,"query_impressions":1616,"query_ctr":0.022896039603960396,"query_position":6.122524752475248},{"query_keys":"wedding venues cairns tablelands","query_clicks":37,"query_impressions":2023,"query_ctr":0.01828966880869995,"query_position":3.531883341571923},{"query_keys":"newborn photography cairns","query_clicks":36,"query_impressions":660,"query_ctr":0.05454545454545454,"query_position":3.8696969696969696}]}