{"month_country_array":[{"month_country_keys":"aus","month_country_clicks":89,"month_country_impressions":11228,"month_country_ctr":0.007926612041325259,"month_country_position":23.934805842536516},{"month_country_keys":"ind","month_country_clicks":5,"month_country_impressions":1181,"month_country_ctr":0.004233700254022015,"month_country_position":49.756138865368335},{"month_country_keys":"phl","month_country_clicks":1,"month_country_impressions":457,"month_country_ctr":0.002188183807439825,"month_country_position":51.44638949671772},{"month_country_keys":"rus","month_country_clicks":1,"month_country_impressions":758,"month_country_ctr":0.0013192612137203166,"month_country_position":51.0131926121372},{"month_country_keys":"usa","month_country_clicks":1,"month_country_impressions":3736,"month_country_ctr":0.0002676659528907923,"month_country_position":51.271948608137045},{"month_country_keys":"abw","month_country_clicks":0,"month_country_impressions":1,"month_country_ctr":0,"month_country_position":87},{"month_country_keys":"afg","month_country_clicks":0,"month_country_impressions":23,"month_country_ctr":0,"month_country_position":65.73913043478261},{"month_country_keys":"ago","month_country_clicks":0,"month_country_impressions":13,"month_country_ctr":0,"month_country_position":54.53846153846154},{"month_country_keys":"alb","month_country_clicks":0,"month_country_impressions":30,"month_country_ctr":0,"month_country_position":69.63333333333334},{"month_country_keys":"and","month_country_clicks":0,"month_country_impressions":1,"month_country_ctr":0,"month_country_position":22}],"three_country_array":[{"threeCountry_keys":"aus","threeCountry_clicks":294,"threeCountry_impressions":37538,"threeCountry_ctr":0.007832063508977569,"threeCountry_position":24.02424210133731},{"threeCountry_keys":"ind","threeCountry_clicks":11,"threeCountry_impressions":3911,"threeCountry_ctr":0.002812579902838149,"threeCountry_position":51.21324469445155},{"threeCountry_keys":"phl","threeCountry_clicks":3,"threeCountry_impressions":1658,"threeCountry_ctr":0.0018094089264173703,"threeCountry_position":51.86007237635706},{"threeCountry_keys":"chn","threeCountry_clicks":2,"threeCountry_impressions":114,"threeCountry_ctr":0.017543859649122806,"threeCountry_position":42.50877192982456},{"threeCountry_keys":"pry","threeCountry_clicks":2,"threeCountry_impressions":111,"threeCountry_ctr":0.018018018018018018,"threeCountry_position":53.03603603603604},{"threeCountry_keys":"usa","threeCountry_clicks":2,"threeCountry_impressions":13072,"threeCountry_ctr":0.0001529987760097919,"threeCountry_position":50.889917380660954},{"threeCountry_keys":"alb","threeCountry_clicks":1,"threeCountry_impressions":86,"threeCountry_ctr":0.011627906976744186,"threeCountry_position":59.58139534883721},{"threeCountry_keys":"bgr","threeCountry_clicks":1,"threeCountry_impressions":184,"threeCountry_ctr":0.005434782608695652,"threeCountry_position":49.28804347826087},{"threeCountry_keys":"egy","threeCountry_clicks":1,"threeCountry_impressions":734,"threeCountry_ctr":0.0013623978201634877,"threeCountry_position":51.0408719346049},{"threeCountry_keys":"gbr","threeCountry_clicks":1,"threeCountry_impressions":977,"threeCountry_ctr":0.0010235414534288639,"threeCountry_position":51.14636642784033}],"six_country_array":[{"six_month_Country_keys":"aus","six_month_Country_clicks":604,"six_month_Country_impressions":70979,"six_month_Country_ctr":0.008509559165386945,"six_month_Country_position":24.013215176319758},{"six_month_Country_keys":"ind","six_month_Country_clicks":31,"six_month_Country_impressions":8561,"six_month_Country_ctr":0.003621072304637309,"six_month_Country_position":50.23817311061792},{"six_month_Country_keys":"phl","six_month_Country_clicks":8,"six_month_Country_impressions":3057,"six_month_Country_ctr":0.0026169447170428526,"six_month_Country_position":51.33496892378149},{"six_month_Country_keys":"alb","six_month_Country_clicks":2,"six_month_Country_impressions":142,"six_month_Country_ctr":0.014084507042253521,"six_month_Country_position":56.90845070422535},{"six_month_Country_keys":"bgd","six_month_Country_clicks":2,"six_month_Country_impressions":1597,"six_month_Country_ctr":0.0012523481527864746,"six_month_Country_position":53.90983093299938},{"six_month_Country_keys":"chn","six_month_Country_clicks":2,"six_month_Country_impressions":130,"six_month_Country_ctr":0.015384615384615385,"six_month_Country_position":42.41538461538462},{"six_month_Country_keys":"hkg","six_month_Country_clicks":2,"six_month_Country_impressions":401,"six_month_Country_ctr":0.004987531172069825,"six_month_Country_position":45.418952618453865},{"six_month_Country_keys":"ken","six_month_Country_clicks":2,"six_month_Country_impressions":316,"six_month_Country_ctr":0.006329113924050633,"six_month_Country_position":48.462025316455694},{"six_month_Country_keys":"pak","six_month_Country_clicks":2,"six_month_Country_impressions":1903,"six_month_Country_ctr":0.0010509721492380452,"six_month_Country_position":53.730425643720444},{"six_month_Country_keys":"pry","six_month_Country_clicks":2,"six_month_Country_impressions":193,"six_month_Country_ctr":0.010362694300518135,"six_month_Country_position":54.409326424870464}],"nine_country_array":[{"nine_month_Country_keys":"aus","nine_month_Country_clicks":957,"nine_month_Country_impressions":100536,"nine_month_Country_ctr":0.009518978276438292,"nine_month_Country_position":24.20025662449272},{"nine_month_Country_keys":"ind","nine_month_Country_clicks":53,"nine_month_Country_impressions":13666,"nine_month_Country_ctr":0.003878237962827455,"nine_month_Country_position":49.24103614810478},{"nine_month_Country_keys":"phl","nine_month_Country_clicks":15,"nine_month_Country_impressions":4404,"nine_month_Country_ctr":0.0034059945504087193,"nine_month_Country_position":50.78133514986376},{"nine_month_Country_keys":"alb","nine_month_Country_clicks":6,"nine_month_Country_impressions":191,"nine_month_Country_ctr":0.031413612565445025,"nine_month_Country_position":51.246073298429316},{"nine_month_Country_keys":"hkg","nine_month_Country_clicks":5,"nine_month_Country_impressions":615,"nine_month_Country_ctr":0.008130081300813009,"nine_month_Country_position":45.759349593495934},{"nine_month_Country_keys":"pry","nine_month_Country_clicks":4,"nine_month_Country_impressions":293,"nine_month_Country_ctr":0.013651877133105802,"nine_month_Country_position":52.09556313993174},{"nine_month_Country_keys":"ken","nine_month_Country_clicks":3,"nine_month_Country_impressions":440,"nine_month_Country_ctr":0.006818181818181818,"nine_month_Country_position":49.393181818181816},{"nine_month_Country_keys":"pak","nine_month_Country_clicks":3,"nine_month_Country_impressions":2853,"nine_month_Country_ctr":0.0010515247108307045,"nine_month_Country_position":53.69365580091132},{"nine_month_Country_keys":"usa","nine_month_Country_clicks":3,"nine_month_Country_impressions":39767,"nine_month_Country_ctr":7.543943470716926e-5,"nine_month_Country_position":46.564639022304924},{"nine_month_Country_keys":"are","nine_month_Country_clicks":2,"nine_month_Country_impressions":1097,"nine_month_Country_ctr":0.0018231540565177757,"nine_month_Country_position":48.05013673655424}],"year_country_array":[{"year_Country_keys":"aus","year_Country_clicks":1289,"year_Country_impressions":136440,"year_Country_ctr":0.00944737613603049,"year_Country_position":26.0979624743477},{"year_Country_keys":"ind","year_Country_clicks":77,"year_Country_impressions":17381,"year_Country_ctr":0.004430124848973017,"year_Country_position":49.15597491513722},{"year_Country_keys":"phl","year_Country_clicks":21,"year_Country_impressions":5701,"year_Country_ctr":0.0036835642869671986,"year_Country_position":49.860550780564814},{"year_Country_keys":"pry","year_Country_clicks":7,"year_Country_impressions":403,"year_Country_ctr":0.017369727047146403,"year_Country_position":52.473945409429284},{"year_Country_keys":"alb","year_Country_clicks":6,"year_Country_impressions":215,"year_Country_ctr":0.027906976744186046,"year_Country_position":50.93488372093023},{"year_Country_keys":"usa","year_Country_clicks":6,"year_Country_impressions":49190,"year_Country_ctr":0.00012197601138442773,"year_Country_position":45.401768652165075},{"year_Country_keys":"hkg","year_Country_clicks":5,"year_Country_impressions":751,"year_Country_ctr":0.006657789613848202,"year_Country_position":45.35685752330227},{"year_Country_keys":"bgd","year_Country_clicks":4,"year_Country_impressions":2713,"year_Country_ctr":0.001474382602285293,"year_Country_position":53.27054920751935},{"year_Country_keys":"ken","year_Country_clicks":4,"year_Country_impressions":545,"year_Country_ctr":0.007339449541284404,"year_Country_position":49.242201834862385},{"year_Country_keys":"nzl","year_Country_clicks":3,"year_Country_impressions":441,"year_Country_ctr":0.006802721088435374,"year_Country_position":41.519274376417236}],"two_year_country_array":[{"two_year_Country_keys":"aus","two_year_Country_clicks":1725,"two_year_Country_impressions":182673,"two_year_Country_ctr":0.009443103250069796,"two_year_Country_position":27.60056494391618},{"two_year_Country_keys":"ind","two_year_Country_clicks":93,"two_year_Country_impressions":21493,"two_year_Country_ctr":0.00432699018285023,"two_year_Country_position":47.790908667938396},{"two_year_Country_keys":"phl","two_year_Country_clicks":24,"two_year_Country_impressions":7245,"two_year_Country_ctr":0.0033126293995859213,"two_year_Country_position":48.38205659075224},{"two_year_Country_keys":"pry","two_year_Country_clicks":8,"two_year_Country_impressions":578,"two_year_Country_ctr":0.01384083044982699,"two_year_Country_position":47.45847750865052},{"two_year_Country_keys":"usa","two_year_Country_clicks":8,"two_year_Country_impressions":62668,"two_year_Country_ctr":0.00012765685836471565,"two_year_Country_position":44.956899853194614},{"two_year_Country_keys":"alb","two_year_Country_clicks":7,"two_year_Country_impressions":272,"two_year_Country_ctr":0.025735294117647058,"two_year_Country_position":48.31985294117647},{"two_year_Country_keys":"hkg","two_year_Country_clicks":7,"two_year_Country_impressions":954,"two_year_Country_ctr":0.007337526205450734,"two_year_Country_position":45.62473794549266},{"two_year_Country_keys":"ken","two_year_Country_clicks":5,"two_year_Country_impressions":663,"two_year_Country_ctr":0.007541478129713424,"two_year_Country_position":48.159879336349924},{"two_year_Country_keys":"bgd","two_year_Country_clicks":4,"two_year_Country_impressions":3239,"two_year_Country_ctr":0.001234949058351343,"two_year_Country_position":51.7511577647422},{"two_year_Country_keys":"chn","two_year_Country_clicks":4,"two_year_Country_impressions":165,"two_year_Country_ctr":0.024242424242424242,"two_year_Country_position":41.03636363636364}]}