{"current_three_sm_array":{"three_current_sm_location":["google \/ organic","(direct) \/ (none)","bing \/ organic","sociablelabs.com \/ referral","yahoo \/ organic","Welcome Series \/ email","abandoned_cart \/ email","buttons \/ facebook_messenger","10bestseo.com \/ referral","Jan 05 Non openers \/ email","Jan 7 Clean Non-Openers \/ email","app.leadstoprofit.club \/ referral","baidu \/ organic","dogpile.com \/ referral","duckduckgo \/ organic","facebook.com \/ referral","forum.ecommercefuel.com \/ referral","gear.tripawds.com \/ referral","gopher.com \/ referral","linkauthority.com \/ referral","lm.facebook.com \/ referral","m.facebook.com \/ referral","nullrefer.com \/ referral","pets.nation.com \/ referral","pi.pardot.com \/ referral","salessystem.logicalposition.com \/ referral","search.xfinity.com \/ referral","shipmonk.lightning.force.com \/ referral","shor.by \/ referral","simplycodes.com \/ referral","tineye.com \/ referral","treehugger.com \/ referral","tropicaliafilm.com \/ referral","yotpo \/ email","youtube.com \/ referral"],"three_current_sm_goal":["89","50","3","2","2","1","1","1","0","0","0","0","0","0","0","0","0","0","0","0","0","0","0","0","0","0","0","0","0","0","0","0","0","0","0"]},"prev_three_sm_array":{"three_prev_sm_location":["google \/ organic","(direct) \/ (none)","bing \/ organic","sociablelabs.com \/ referral","yahoo \/ organic","duckduckgo \/ organic","search.aol.com \/ referral","Jan 05 Non openers \/ email","Jan 7 Clean Non-Openers \/ email","Welcome Series \/ email","app.keyword.com \/ referral","baidu \/ organic","betterworldpets.knoji.com \/ referral","buttons \/ facebook_messenger","chewy.custhelp.com \/ referral","cn.bing.com \/ referral","dealdrop-tools.herokuapp.com \/ referral","ecosia.org \/ organic","facebook.com \/ referral","givegoodfoodtoyourmac.com \/ referral","google \/ cpc","l.facebook.com \/ referral","lm.facebook.com \/ referral","m.facebook.com \/ referral","municipalitedeboltonouest.com \/ referral","pinterest.com \/ referral","risa-tester.s3.amazonaws.com \/ referral","rubyhas.lightning.force.com \/ referral","salessystem.logicalposition.com \/ referral","search.aol.co.uk \/ referral","search.frontier.com \/ referral","shop_app \/ (not set)","shopinspect.com \/ referral","shor.by \/ referral","simplycodes.com \/ referral","thedatashift.org \/ referral","wap.sogou.com \/ referral","websites.godaddy.com \/ referral","yotpo \/ email","youtube.com \/ referral"],"three_prev_sm_goal":["83","50","9","7","7","3","1","0","0","0","0","0","0","0","0","0","0","0","0","0","0","0","0","0","0","0","0","0","0","0","0","0","0","0","0","0","0","0","0","0"]},"current_three_sm_organic_array":{"three_current_organic_sm_location":["bing \/ organic","google \/ organic","yahoo \/ organic"],"three_current_organic_sm_goal":["3","89","2"]},"prev_three_sm_organic_array":{"three_prev_organic_sm_location":["bing \/ organic","duckduckgo \/ organic","google \/ organic","yahoo \/ organic"],"three_prev_organic_sm_goal":["9","3","83","7"]}}