{"month_query_array":[],"three_query_array":[{"three_query_keys":"fun fun app","three_query_clicks":0,"three_query_impressions":1,"three_query_ctr":0,"three_query_position":38},{"three_query_keys":"funfun","three_query_clicks":0,"three_query_impressions":1,"three_query_ctr":0,"three_query_position":33},{"three_query_keys":"funmiles app","three_query_clicks":0,"three_query_impressions":1,"three_query_ctr":0,"three_query_position":91},{"three_query_keys":"funnearn app","three_query_clicks":0,"three_query_impressions":1,"three_query_ctr":0,"three_query_position":95},{"three_query_keys":"funu app","three_query_clicks":0,"three_query_impressions":1,"three_query_ctr":0,"three_query_position":98},{"three_query_keys":"happy fun land","three_query_clicks":0,"three_query_impressions":2,"three_query_ctr":0,"three_query_position":97.5},{"three_query_keys":"my fun land","three_query_clicks":0,"three_query_impressions":1,"three_query_ctr":0,"three_query_position":98}],"six_query_array":[{"six_query_keys":"fun fun app","six_query_clicks":0,"six_query_impressions":1,"six_query_ctr":0,"six_query_position":38},{"six_query_keys":"funfun","six_query_clicks":0,"six_query_impressions":1,"six_query_ctr":0,"six_query_position":33},{"six_query_keys":"funmiles app","six_query_clicks":0,"six_query_impressions":1,"six_query_ctr":0,"six_query_position":91},{"six_query_keys":"funnearn app","six_query_clicks":0,"six_query_impressions":1,"six_query_ctr":0,"six_query_position":95},{"six_query_keys":"funu app","six_query_clicks":0,"six_query_impressions":1,"six_query_ctr":0,"six_query_position":98},{"six_query_keys":"happy fun land","six_query_clicks":0,"six_query_impressions":2,"six_query_ctr":0,"six_query_position":97.5},{"six_query_keys":"my fun land","six_query_clicks":0,"six_query_impressions":1,"six_query_ctr":0,"six_query_position":98}],"nine_query_array":[{"nine_query_keys":"fun fun app","nine_query_clicks":0,"nine_query_impressions":1,"nine_query_ctr":0,"nine_query_position":38},{"nine_query_keys":"funfun","nine_query_clicks":0,"nine_query_impressions":1,"nine_query_ctr":0,"nine_query_position":33},{"nine_query_keys":"funmiles app","nine_query_clicks":0,"nine_query_impressions":1,"nine_query_ctr":0,"nine_query_position":91},{"nine_query_keys":"funnearn app","nine_query_clicks":0,"nine_query_impressions":1,"nine_query_ctr":0,"nine_query_position":95},{"nine_query_keys":"funu app","nine_query_clicks":0,"nine_query_impressions":1,"nine_query_ctr":0,"nine_query_position":98},{"nine_query_keys":"happy fun land","nine_query_clicks":0,"nine_query_impressions":2,"nine_query_ctr":0,"nine_query_position":97.5},{"nine_query_keys":"my fun land","nine_query_clicks":0,"nine_query_impressions":1,"nine_query_ctr":0,"nine_query_position":98}],"one_year_query_array":[{"one_year_query_keys":"fun fun app","one_year_query_clicks":0,"one_year_query_impressions":1,"one_year_query_ctr":0,"one_year_query_position":38},{"one_year_query_keys":"funfun","one_year_query_clicks":0,"one_year_query_impressions":1,"one_year_query_ctr":0,"one_year_query_position":33},{"one_year_query_keys":"funmiles app","one_year_query_clicks":0,"one_year_query_impressions":1,"one_year_query_ctr":0,"one_year_query_position":91},{"one_year_query_keys":"funnearn app","one_year_query_clicks":0,"one_year_query_impressions":1,"one_year_query_ctr":0,"one_year_query_position":95},{"one_year_query_keys":"funu app","one_year_query_clicks":0,"one_year_query_impressions":1,"one_year_query_ctr":0,"one_year_query_position":98},{"one_year_query_keys":"happy fun land","one_year_query_clicks":0,"one_year_query_impressions":2,"one_year_query_ctr":0,"one_year_query_position":97.5},{"one_year_query_keys":"my fun land","one_year_query_clicks":0,"one_year_query_impressions":1,"one_year_query_ctr":0,"one_year_query_position":98}],"two_year_query_array":[{"query_keys":"fun fun app","query_clicks":0,"query_impressions":1,"query_ctr":0,"query_position":38},{"query_keys":"funfun","query_clicks":0,"query_impressions":1,"query_ctr":0,"query_position":33},{"query_keys":"funmiles app","query_clicks":0,"query_impressions":1,"query_ctr":0,"query_position":91},{"query_keys":"funnearn app","query_clicks":0,"query_impressions":1,"query_ctr":0,"query_position":95},{"query_keys":"funu app","query_clicks":0,"query_impressions":1,"query_ctr":0,"query_position":98},{"query_keys":"happy fun land","query_clicks":0,"query_impressions":2,"query_ctr":0,"query_position":97.5},{"query_keys":"my fun land","query_clicks":0,"query_impressions":1,"query_ctr":0,"query_position":98}]}