{"month_device_array":[{"month_device_keys":"DESKTOP","month_device_clicks":31,"month_device_impressions":3493,"month_device_ctr":0.008874892642427712,"month_device_position":42.61465788720298},{"month_device_keys":"MOBILE","month_device_clicks":11,"month_device_impressions":461,"month_device_ctr":0.02386117136659436,"month_device_position":31.893709327548805},{"month_device_keys":"TABLET","month_device_clicks":0,"month_device_impressions":6,"month_device_ctr":0,"month_device_position":18.666666666666668}],"three_device_array":[{"three_device_keys":"DESKTOP","three_device_clicks":101,"three_device_impressions":12152,"three_device_ctr":0.008311389071757736,"three_device_position":41.61734693877551},{"three_device_keys":"MOBILE","three_device_clicks":46,"three_device_impressions":1780,"three_device_ctr":0.025842696629213482,"three_device_position":30.587078651685392},{"three_device_keys":"TABLET","three_device_clicks":0,"three_device_impressions":33,"three_device_ctr":0,"three_device_position":8.878787878787879}],"six_device_array":[{"six_device_keys":"DESKTOP","six_device_clicks":263,"six_device_impressions":21601,"six_device_ctr":0.012175362251747604,"six_device_position":40.591130040275914},{"six_device_keys":"MOBILE","six_device_clicks":95,"six_device_impressions":3112,"six_device_ctr":0.030526992287917738,"six_device_position":29.50578406169666},{"six_device_keys":"TABLET","six_device_clicks":4,"six_device_impressions":67,"six_device_ctr":0.05970149253731343,"six_device_position":6.850746268656716}],"nine_device_array":[{"nine_device_keys":"DESKTOP","nine_device_clicks":400,"nine_device_impressions":26449,"nine_device_ctr":0.015123445120798518,"nine_device_position":40.47079284661046},{"nine_device_keys":"MOBILE","nine_device_clicks":123,"nine_device_impressions":3964,"nine_device_ctr":0.031029263370333,"nine_device_position":27.988900100908175},{"nine_device_keys":"TABLET","nine_device_clicks":4,"nine_device_impressions":90,"nine_device_ctr":0.044444444444444446,"nine_device_position":9.522222222222222}],"year_device_array":[{"year_device_keys":"DESKTOP","year_device_clicks":479,"year_device_impressions":29373,"year_device_ctr":0.01630749327613795,"year_device_position":39.372995608211625},{"year_device_keys":"MOBILE","year_device_clicks":151,"year_device_impressions":4761,"year_device_ctr":0.03171602604494854,"year_device_position":27.58958202058391},{"year_device_keys":"TABLET","year_device_clicks":4,"year_device_impressions":112,"year_device_ctr":0.03571428571428571,"year_device_position":10.955357142857142}],"two_year_device_array":[{"two_year_device_keys":"DESKTOP","two_year_device_clicks":548,"two_year_device_impressions":32493,"two_year_device_ctr":0.016865170959899055,"two_year_device_position":38.29846428461515},{"two_year_device_keys":"MOBILE","two_year_device_clicks":174,"two_year_device_impressions":5715,"two_year_device_ctr":0.030446194225721784,"two_year_device_position":26.889588801399825},{"two_year_device_keys":"TABLET","two_year_device_clicks":7,"two_year_device_impressions":143,"two_year_device_ctr":0.04895104895104895,"two_year_device_position":11.125874125874127}]}