{"month_page_array":[{"month_page_keys":"https:\/\/www.essentialstaff.co.uk\/jobs\/hospitality-and-catering\/","month_page_clicks":5,"month_page_impressions":3104},{"month_page_keys":"https:\/\/www.essentialstaff.co.uk\/contact\/","month_page_clicks":1,"month_page_impressions":7},{"month_page_keys":"https:\/\/www.essentialstaff.co.uk\/jobs\/beauty-and-wellness\/","month_page_clicks":1,"month_page_impressions":1125},{"month_page_keys":"https:\/\/www.essentialstaff.co.uk\/jobs\/events-and-entertainment\/","month_page_clicks":1,"month_page_impressions":395},{"month_page_keys":"https:\/\/www.essentialstaff.co.uk\/about\/","month_page_clicks":0,"month_page_impressions":15},{"month_page_keys":"https:\/\/www.essentialstaff.co.uk\/faq\/","month_page_clicks":0,"month_page_impressions":22},{"month_page_keys":"https:\/\/www.essentialstaff.co.uk\/findjobs\/","month_page_clicks":0,"month_page_impressions":566},{"month_page_keys":"https:\/\/www.essentialstaff.co.uk\/hirestaff\/","month_page_clicks":0,"month_page_impressions":26},{"month_page_keys":"https:\/\/www.essentialstaff.co.uk\/jobs\/admin-and-office\/","month_page_clicks":0,"month_page_impressions":1},{"month_page_keys":"https:\/\/www.essentialstaff.co.uk\/jobs\/housekeeping-and-maintenance\/","month_page_clicks":0,"month_page_impressions":701}],"three_page_array":[{"three_page_keys":"https:\/\/www.essentialstaff.co.uk\/","three_page_clicks":65,"three_page_impressions":1447},{"three_page_keys":"https:\/\/www.essentialstaff.co.uk\/jobs\/hospitality-and-catering\/","three_page_clicks":5,"three_page_impressions":3856},{"three_page_keys":"https:\/\/www.essentialstaff.co.uk\/jobs\/beauty-and-wellness\/","three_page_clicks":2,"three_page_impressions":1653},{"three_page_keys":"https:\/\/www.essentialstaff.co.uk\/contact\/","three_page_clicks":1,"three_page_impressions":26},{"three_page_keys":"https:\/\/www.essentialstaff.co.uk\/jobs\/events-and-entertainment\/","three_page_clicks":1,"three_page_impressions":471},{"three_page_keys":"https:\/\/www.essentialstaff.co.uk\/about\/","three_page_clicks":0,"three_page_impressions":39},{"three_page_keys":"https:\/\/www.essentialstaff.co.uk\/demo\/","three_page_clicks":0,"three_page_impressions":10},{"three_page_keys":"https:\/\/www.essentialstaff.co.uk\/faq\/","three_page_clicks":0,"three_page_impressions":33},{"three_page_keys":"https:\/\/www.essentialstaff.co.uk\/features\/","three_page_clicks":0,"three_page_impressions":2},{"three_page_keys":"https:\/\/www.essentialstaff.co.uk\/findjobs\/","three_page_clicks":0,"three_page_impressions":639}],"six_page_array":[{"six_page_keys":"https:\/\/www.essentialstaff.co.uk\/","six_page_clicks":122,"six_page_impressions":2798},{"six_page_keys":"https:\/\/www.essentialstaff.co.uk\/jobs\/hospitality-and-catering\/","six_page_clicks":5,"six_page_impressions":3873},{"six_page_keys":"https:\/\/www.essentialstaff.co.uk\/jobs\/beauty-and-wellness\/","six_page_clicks":2,"six_page_impressions":1684},{"six_page_keys":"https:\/\/www.essentialstaff.co.uk\/about-us\/","six_page_clicks":1,"six_page_impressions":5},{"six_page_keys":"https:\/\/www.essentialstaff.co.uk\/contact\/","six_page_clicks":1,"six_page_impressions":34},{"six_page_keys":"https:\/\/www.essentialstaff.co.uk\/jobs\/events-and-entertainment\/","six_page_clicks":1,"six_page_impressions":472},{"six_page_keys":"https:\/\/www.essentialstaff.co.uk\/the-app\/","six_page_clicks":1,"six_page_impressions":32},{"six_page_keys":"https:\/\/www.essentialstaff.co.uk\/about\/","six_page_clicks":0,"six_page_impressions":57},{"six_page_keys":"https:\/\/www.essentialstaff.co.uk\/demo\/","six_page_clicks":0,"six_page_impressions":15},{"six_page_keys":"https:\/\/www.essentialstaff.co.uk\/faq\/","six_page_clicks":0,"six_page_impressions":44}],"nine_page_array":[{"nine_page_keys":"https:\/\/www.essentialstaff.co.uk\/","nine_page_clicks":122,"nine_page_impressions":2798},{"nine_page_keys":"https:\/\/www.essentialstaff.co.uk\/jobs\/hospitality-and-catering\/","nine_page_clicks":5,"nine_page_impressions":3873},{"nine_page_keys":"https:\/\/www.essentialstaff.co.uk\/jobs\/beauty-and-wellness\/","nine_page_clicks":2,"nine_page_impressions":1684},{"nine_page_keys":"https:\/\/www.essentialstaff.co.uk\/about-us\/","nine_page_clicks":1,"nine_page_impressions":5},{"nine_page_keys":"https:\/\/www.essentialstaff.co.uk\/contact\/","nine_page_clicks":1,"nine_page_impressions":34},{"nine_page_keys":"https:\/\/www.essentialstaff.co.uk\/jobs\/events-and-entertainment\/","nine_page_clicks":1,"nine_page_impressions":472},{"nine_page_keys":"https:\/\/www.essentialstaff.co.uk\/the-app\/","nine_page_clicks":1,"nine_page_impressions":32},{"nine_page_keys":"https:\/\/www.essentialstaff.co.uk\/about\/","nine_page_clicks":0,"nine_page_impressions":57},{"nine_page_keys":"https:\/\/www.essentialstaff.co.uk\/demo\/","nine_page_clicks":0,"nine_page_impressions":15},{"nine_page_keys":"https:\/\/www.essentialstaff.co.uk\/faq\/","nine_page_clicks":0,"nine_page_impressions":44}],"year_page_array":[{"year_page_keys":"https:\/\/www.essentialstaff.co.uk\/","year_page_clicks":122,"year_page_impressions":2798},{"year_page_keys":"https:\/\/www.essentialstaff.co.uk\/jobs\/hospitality-and-catering\/","year_page_clicks":5,"year_page_impressions":3873},{"year_page_keys":"https:\/\/www.essentialstaff.co.uk\/jobs\/beauty-and-wellness\/","year_page_clicks":2,"year_page_impressions":1684},{"year_page_keys":"https:\/\/www.essentialstaff.co.uk\/about-us\/","year_page_clicks":1,"year_page_impressions":5},{"year_page_keys":"https:\/\/www.essentialstaff.co.uk\/contact\/","year_page_clicks":1,"year_page_impressions":34},{"year_page_keys":"https:\/\/www.essentialstaff.co.uk\/jobs\/events-and-entertainment\/","year_page_clicks":1,"year_page_impressions":472},{"year_page_keys":"https:\/\/www.essentialstaff.co.uk\/the-app\/","year_page_clicks":1,"year_page_impressions":32},{"year_page_keys":"https:\/\/www.essentialstaff.co.uk\/about\/","year_page_clicks":0,"year_page_impressions":57},{"year_page_keys":"https:\/\/www.essentialstaff.co.uk\/demo\/","year_page_clicks":0,"year_page_impressions":15},{"year_page_keys":"https:\/\/www.essentialstaff.co.uk\/faq\/","year_page_clicks":0,"year_page_impressions":44}],"two_year_page_array":[{"two_year_page_keys":"https:\/\/www.essentialstaff.co.uk\/","two_year_page_clicks":122,"two_year_page_impressions":2798},{"two_year_page_keys":"https:\/\/www.essentialstaff.co.uk\/jobs\/hospitality-and-catering\/","two_year_page_clicks":5,"two_year_page_impressions":3873},{"two_year_page_keys":"https:\/\/www.essentialstaff.co.uk\/jobs\/beauty-and-wellness\/","two_year_page_clicks":2,"two_year_page_impressions":1684},{"two_year_page_keys":"https:\/\/www.essentialstaff.co.uk\/about-us\/","two_year_page_clicks":1,"two_year_page_impressions":5},{"two_year_page_keys":"https:\/\/www.essentialstaff.co.uk\/contact\/","two_year_page_clicks":1,"two_year_page_impressions":34},{"two_year_page_keys":"https:\/\/www.essentialstaff.co.uk\/jobs\/events-and-entertainment\/","two_year_page_clicks":1,"two_year_page_impressions":472},{"two_year_page_keys":"https:\/\/www.essentialstaff.co.uk\/the-app\/","two_year_page_clicks":1,"two_year_page_impressions":32},{"two_year_page_keys":"https:\/\/www.essentialstaff.co.uk\/about\/","two_year_page_clicks":0,"two_year_page_impressions":57},{"two_year_page_keys":"https:\/\/www.essentialstaff.co.uk\/demo\/","two_year_page_clicks":0,"two_year_page_impressions":15},{"two_year_page_keys":"https:\/\/www.essentialstaff.co.uk\/faq\/","two_year_page_clicks":0,"two_year_page_impressions":44}]}