{"month_device_array":[{"month_device_keys":"MOBILE","month_device_clicks":370,"month_device_impressions":16479,"month_device_ctr":0.02245281873900115,"month_device_position":24.109229929000545},{"month_device_keys":"DESKTOP","month_device_clicks":183,"month_device_impressions":18936,"month_device_ctr":0.009664131812420786,"month_device_position":43.130016899028305},{"month_device_keys":"TABLET","month_device_clicks":3,"month_device_impressions":134,"month_device_ctr":0.022388059701492536,"month_device_position":13.365671641791044}],"three_device_array":[{"three_device_keys":"MOBILE","three_device_clicks":1186,"three_device_impressions":48625,"three_device_ctr":0.02439074550128535,"three_device_position":23.950231362467868},{"three_device_keys":"DESKTOP","three_device_clicks":593,"three_device_impressions":55317,"three_device_ctr":0.01072003181662057,"three_device_position":43.26581340275141},{"three_device_keys":"TABLET","three_device_clicks":16,"three_device_impressions":452,"three_device_ctr":0.035398230088495575,"three_device_position":15.43141592920354}],"six_device_array":[{"six_device_keys":"MOBILE","six_device_clicks":2416,"six_device_impressions":88801,"six_device_ctr":0.02720690082318893,"six_device_position":22.318746410513395},{"six_device_keys":"DESKTOP","six_device_clicks":1198,"six_device_impressions":114246,"six_device_ctr":0.01048614393501742,"six_device_position":43.635855959946085},{"six_device_keys":"TABLET","six_device_clicks":33,"six_device_impressions":913,"six_device_ctr":0.03614457831325301,"six_device_position":16.741511500547645}],"nine_device_array":[],"year_device_array":[{"year_device_keys":"MOBILE","year_device_clicks":4364,"year_device_impressions":154784,"year_device_ctr":0.028194128592102543,"year_device_position":21.72528814347736},{"year_device_keys":"DESKTOP","year_device_clicks":2205,"year_device_impressions":211338,"year_device_ctr":0.010433523549953156,"year_device_position":44.295909869498146},{"year_device_keys":"TABLET","year_device_clicks":69,"year_device_impressions":2199,"year_device_ctr":0.03137789904502047,"year_device_position":25.773533424283766}],"two_year_device_array":[{"two_year_device_keys":"MOBILE","two_year_device_clicks":5007,"two_year_device_impressions":188537,"two_year_device_ctr":0.02655712141383389,"two_year_device_position":22.25987471955107},{"two_year_device_keys":"DESKTOP","two_year_device_clicks":2568,"two_year_device_impressions":272557,"two_year_device_ctr":0.009421882395242095,"two_year_device_position":43.434276133065744},{"two_year_device_keys":"TABLET","two_year_device_clicks":83,"two_year_device_impressions":2775,"two_year_device_ctr":0.02990990990990991,"two_year_device_position":24.064504504504505}]}