{"current_nine_sm_array":{"nine_current_sm_location":["google \/ organic","(direct) \/ (none)","tuugo.co.nz \/ referral","baidu \/ organic","bing \/ organic","blog.borg.digital \/ referral","cn.bing.com \/ referral","crmplus.zoho.com \/ referral","duckduckgo \/ organic","ecosia.org \/ organic","facebook.com \/ referral","facilities-integrate \/ website-referral","foodtechnology.co.nz \/ referral","globaleagle.joinf.com \/ referral","hs_email \/ email","linkedin.com \/ referral","lm.facebook.com \/ referral","m.facebook.com \/ referral","mailchi.mp \/ referral","municipalitedeboltonouest.com \/ referral","nz.search.yahoo.com \/ referral","ojifs.lightning.force.com \/ referral","shinysearch.com \/ referral","web.skype.com \/ referral","yahoo \/ organic","yandex \/ organic"],"nine_current_sm_goal":["3","2","1","0","0","0","0","0","0","0","0","0","0","0","0","0","0","0","0","0","0","0","0","0","0","0"]},"prev_nine_sm_array":{"nine_prev_sm_location":[],"nine_prev_sm_goal":[]},"current_nine_sm_organic_array":{"nine_current_organic_sm_location":["google \/ organic"],"nine_current_organic_sm_goal":["3"]},"prev_nine_sm_organic_array":{"nine_prev_organic_sm_location":[],"nine_prev_organic_sm_goal":[]}}